LICENSE
MANIFEST.in
README
README.rst
requirements.txt
setup.py
jinja2_maps/__init__.py
jinja2_maps/apple_maps.py
jinja2_maps/base.py
jinja2_maps/bing_maps.py
jinja2_maps/gmaps.py
jinja2_maps/mappy.py
jinja2_maps/osm.py
jinja2_maps.egg-info/PKG-INFO
jinja2_maps.egg-info/SOURCES.txt
jinja2_maps.egg-info/dependency_links.txt
jinja2_maps.egg-info/requires.txt
jinja2_maps.egg-info/top_level.txt