Metadata-Version: 1.1
Name: jinja2-maps
Version: 0.2.0
Summary: Maps filters for Jinja2
Home-page: https://github.com/bfontaine/jinja2_maps
Author: Baptiste Fontaine
Author-email: b@ptistefontaine.fr
License: Copyright © 2016 – Baptiste Fontaine
